[
  {
    "full_name": "microsoft/foss-fund",
    "stargazers_count": 224,
    "open_issues_count": 0,
    "forks_count": 17
  },
  {
    "full_name": "dotnet/BenchmarkDotNet",
    "stargazers_count": 8365,
    "open_issues_count": 192,
    "forks_count": 832
  },
  {
    "full_name": "SiliconLabs/gecko_sdk",
    "stargazers_count": 145,
    "open_issues_count": 19,
    "forks_count": 62
  },
  {
    "full_name": "bytewizer/runtime",
    "stargazers_count": 6,
    "open_issues_count": 0,
    "forks_count": 2
  },
  {
    "full_name": "Azure/iot-plugandplay-models",
    "stargazers_count": 46,
    "open_issues_count": 2,
    "forks_count": 212
  },
  {
    "full_name": "Azure/DotNetty",
    "stargazers_count": 3717,
    "open_issues_count": 163,
    "forks_count": 933
  },
  {
    "full_name": "Azure/azure-iot-sdk-csharp",
    "stargazers_count": 409,
    "open_issues_count": 29,
    "forks_count": 477
  },
  {
    "full_name": "charlesnicholson/nanoprintf",
    "stargazers_count": 460,
    "open_issues_count": 8,
    "forks_count": 29
  },
  {
    "full_name": "KirillOsenkov/MSBuildStructuredLog",
    "stargazers_count": 1217,
    "open_issues_count": 129,
    "forks_count": 160
  },
  {
    "full_name": "hassio-addons/addon-vscode",
    "stargazers_count": 326,
    "open_issues_count": 2,
    "forks_count": 70
  },
  {
    "full_name": "net-daemon/netdaemon",
    "stargazers_count": 134,
    "open_issues_count": 8,
    "forks_count": 37
  },
  {
    "full_name": "net-daemon/homeassistant-addon",
    "stargazers_count": 9,
    "open_issues_count": 0,
    "forks_count": 7
  },
  {
    "full_name": "net-daemon/docs",
    "stargazers_count": 27,
    "open_issues_count": 4,
    "forks_count": 23
  },
  {
    "full_name": "Azure-Samples/azure-iot-samples-csharp",
    "stargazers_count": 197,
    "open_issues_count": 0,
    "forks_count": 234
  },
  {
    "full_name": "Azure/iot-central-industrial-OEE",
    "stargazers_count": 20,
    "open_issues_count": 1,
    "forks_count": 4
  },
  {
    "full_name": "AArnott/Nerdbank.Streams",
    "stargazers_count": 383,
    "open_issues_count": 11,
    "forks_count": 40
  },
  {
    "full_name": "nanoframework/System.Net.Sockets.TcpClient",
    "stargazers_count": 3,
    "open_issues_count": 0,
    "forks_count": 2
  },
  {
    "full_name": "microsoft/jacdac-stm32x0",
    "stargazers_count": 11,
    "open_issues_count": 4,
    "forks_count": 7
  },
  {
    "full_name": "Azure/azure-sdk-for-c",
    "stargazers_count": 168,
    "open_issues_count": 99,
    "forks_count": 106
  },
  {
    "full_name": "aormsby/Fork-Sync-With-Upstream-action",
    "stargazers_count": 122,
    "open_issues_count": 6,
    "forks_count": 44
  },
  {
    "full_name": "nanoframework/System.Net.Sockets.UdpClient",
    "stargazers_count": 3,
    "open_issues_count": 0,
    "forks_count": 2
  },
  {
    "full_name": "carlosperate/arm-none-eabi-gcc-action",
    "stargazers_count": 18,
    "open_issues_count": 5,
    "forks_count": 2
  },
  {
    "full_name": "nanoframework/nanoFramework.SignalR.Client",
    "stargazers_count": 8,
    "open_issues_count": 0,
    "forks_count": 3
  },
  {
    "full_name": "angularsen/UnitsNet",
    "stargazers_count": 1741,
    "open_issues_count": 29,
    "forks_count": 311
  },
  {
    "full_name": "nanoframework/nanobuild",
    "stargazers_count": 3,
    "open_issues_count": 0,
    "forks_count": 1
  },
  {
    "full_name": "microsoft/jacdac-ddk",
    "stargazers_count": 16,
    "open_issues_count": 0,
    "forks_count": 8
  },
  {
    "full_name": "microsoft/jacdac-esp32",
    "stargazers_count": 4,
    "open_issues_count": 0,
    "forks_count": 0
  },
  {
    "full_name": "microsoft/jacdac-dotnet",
    "stargazers_count": 11,
    "open_issues_count": 1,
    "forks_count": 4
  },
  {
    "full_name": "bytewizer/blueswireless",
    "stargazers_count": 6,
    "open_issues_count": 0,
    "forks_count": 2
  },
  {
    "full_name": "github/copilot-docs",
    "stargazers_count": 21303,
    "open_issues_count": 18,
    "forks_count": 2369
  }
]