[
  {
    "full_name": "Ellerbach/docfx-companion-tools",
    "stargazers_count": 30,
    "open_issues_count": 2,
    "forks_count": 11
  },
  {
    "full_name": "Apress/exp-.net-micro-framework",
    "stargazers_count": 2,
    "open_issues_count": 0,
    "forks_count": 3
  },
  {
    "full_name": "wasm3/wasm3",
    "stargazers_count": 5596,
    "open_issues_count": 45,
    "forks_count": 364
  },
  {
    "full_name": "cnlohr/mini-rv32ima",
    "stargazers_count": 688,
    "open_issues_count": 6,
    "forks_count": 32
  },
  {
    "full_name": "microsoft/foss-fund",
    "stargazers_count": 231,
    "open_issues_count": 0,
    "forks_count": 17
  },
  {
    "full_name": "dotnet/BenchmarkDotNet",
    "stargazers_count": 8483,
    "open_issues_count": 195,
    "forks_count": 842
  },
  {
    "full_name": "SiliconLabs/gecko_sdk",
    "stargazers_count": 160,
    "open_issues_count": 21,
    "forks_count": 66
  },
  {
    "full_name": "bytewizer/runtime",
    "stargazers_count": 6,
    "open_issues_count": 0,
    "forks_count": 2
  },
  {
    "full_name": "Azure/iot-plugandplay-models",
    "stargazers_count": 47,
    "open_issues_count": 2,
    "forks_count": 213
  },
  {
    "full_name": "Azure/DotNetty",
    "stargazers_count": 3736,
    "open_issues_count": 163,
    "forks_count": 932
  },
  {
    "full_name": "Azure/azure-iot-sdk-csharp",
    "stargazers_count": 415,
    "open_issues_count": 24,
    "forks_count": 478
  },
  {
    "full_name": "charlesnicholson/nanoprintf",
    "stargazers_count": 463,
    "open_issues_count": 8,
    "forks_count": 32
  },
  {
    "full_name": "KirillOsenkov/MSBuildStructuredLog",
    "stargazers_count": 1227,
    "open_issues_count": 132,
    "forks_count": 165
  },
  {
    "full_name": "hassio-addons/addon-vscode",
    "stargazers_count": 331,
    "open_issues_count": 4,
    "forks_count": 70
  },
  {
    "full_name": "net-daemon/netdaemon",
    "stargazers_count": 135,
    "open_issues_count": 18,
    "forks_count": 39
  },
  {
    "full_name": "net-daemon/homeassistant-addon",
    "stargazers_count": 9,
    "open_issues_count": 0,
    "forks_count": 8
  },
  {
    "full_name": "net-daemon/docs",
    "stargazers_count": 29,
    "open_issues_count": 4,
    "forks_count": 23
  },
  {
    "full_name": "Azure-Samples/azure-iot-samples-csharp",
    "stargazers_count": 197,
    "open_issues_count": 0,
    "forks_count": 234
  },
  {
    "full_name": "Azure/iot-central-industrial-OEE",
    "stargazers_count": 20,
    "open_issues_count": 1,
    "forks_count": 4
  },
  {
    "full_name": "AArnott/Nerdbank.Streams",
    "stargazers_count": 393,
    "open_issues_count": 12,
    "forks_count": 42
  },
  {
    "full_name": "nanoframework/System.Net.Sockets.TcpClient",
    "stargazers_count": 3,
    "open_issues_count": 0,
    "forks_count": 2
  },
  {
    "full_name": "microsoft/jacdac-stm32x0",
    "stargazers_count": 11,
    "open_issues_count": 4,
    "forks_count": 7
  },
  {
    "full_name": "Azure/azure-sdk-for-c",
    "stargazers_count": 171,
    "open_issues_count": 105,
    "forks_count": 105
  },
  {
    "full_name": "aormsby/Fork-Sync-With-Upstream-action",
    "stargazers_count": 128,
    "open_issues_count": 10,
    "forks_count": 46
  },
  {
    "full_name": "nanoframework/System.Net.Sockets.UdpClient",
    "stargazers_count": 3,
    "open_issues_count": 0,
    "forks_count": 2
  },
  {
    "full_name": "carlosperate/arm-none-eabi-gcc-action",
    "stargazers_count": 19,
    "open_issues_count": 5,
    "forks_count": 2
  },
  {
    "full_name": "nanoframework/nanoFramework.SignalR.Client",
    "stargazers_count": 8,
    "open_issues_count": 0,
    "forks_count": 3
  },
  {
    "full_name": "angularsen/UnitsNet",
    "stargazers_count": 1760,
    "open_issues_count": 25,
    "forks_count": 318
  },
  {
    "full_name": "nanoframework/nanobuild",
    "stargazers_count": 3,
    "open_issues_count": 0,
    "forks_count": 1
  },
  {
    "full_name": "microsoft/jacdac-ddk",
    "stargazers_count": 16,
    "open_issues_count": 0,
    "forks_count": 8
  }
]